shahanshahi_calendar/__init__.py
shahanshahi_calendar/day_names.py
shahanshahi_calendar/occasions.py
shahanshahi_calendar-0.1.2.dist-info/licenses/LICENSE
tests/__init__.py
tests/test_shahanshahi_calendar.py
shahanshahi_calendar-0.1.2.dist-info/METADATA
shahanshahi_calendar-0.1.2.dist-info/WHEEL
shahanshahi_calendar-0.1.2.dist-info/top_level.txt
shahanshahi_calendar-0.1.2.dist-info/RECORD
