Metadata-Version: 2.4
Name: shahanshahi_calendar
Version: 0.1.2
Summary: The Imperial (Shahanshahi) calendar system for Python
Author: Morteza Shoeibi
Author-email: Morteza Shoeibi <mortezashoeibi77@gmail.com>
License: Python Software Foundation License
Requires-Python: >=3.7
License-File: LICENSE
Requires-Dist: jdatetime
Dynamic: author
Dynamic: license-file
Dynamic: requires-python
